experimental_tasks/historical_clustering.py
experimental_tasks/muni_intent_classification.py
experimental_tasks/swedn_sts.py
scripts/check_benchmark_is_up_to_date.py
seb/__init__.py
seb/__main__.py
seb/benchmark.py
seb/full_benchmark.py
seb/py.typed
seb/registries.py
seb/result_dataclasses.py
seb/warning_ignore_manager.py
seb/cache/BAAI__bge-m3/Angry_Tweets.json
seb/cache/BAAI__bge-m3/Bornholm_Parallel.json
seb/cache/BAAI__bge-m3/DKHate.json
seb/cache/BAAI__bge-m3/DaLAJ.json
seb/cache/BAAI__bge-m3/Da_Political_Comments.json
seb/cache/BAAI__bge-m3/DanFEVER.json
seb/cache/BAAI__bge-m3/LCC.json
seb/cache/BAAI__bge-m3/Language_Identification.json
seb/cache/BAAI__bge-m3/Massive_Intent.json
seb/cache/BAAI__bge-m3/Massive_Scenario.json
seb/cache/BAAI__bge-m3/NoReC.json
seb/cache/BAAI__bge-m3/NorQuad.json
seb/cache/BAAI__bge-m3/Norwegian_courts.json
seb/cache/BAAI__bge-m3/Norwegian_parliament.json
seb/cache/BAAI__bge-m3/SNL_Clustering.json
seb/cache/BAAI__bge-m3/SNL_Retrieval.json
seb/cache/BAAI__bge-m3/ScaLA.json
seb/cache/BAAI__bge-m3/Speed_(CPU).json
seb/cache/BAAI__bge-m3/SweFAQ.json
seb/cache/BAAI__bge-m3/SweReC.json
seb/cache/BAAI__bge-m3/SwednClustering.json
seb/cache/BAAI__bge-m3/SwednRetrieval.json
seb/cache/BAAI__bge-m3/TV2Nord_Retrieval.json
seb/cache/BAAI__bge-m3/Twitterhjerne.json
seb/cache/BAAI__bge-m3/VG_Clustering.json
seb/cache/KBLab__sentence-bert-swedish-cased/Angry_Tweets.json
seb/cache/KBLab__sentence-bert-swedish-cased/Bornholm_Parallel.json
seb/cache/KBLab__sentence-bert-swedish-cased/DKHate.json
seb/cache/KBLab__sentence-bert-swedish-cased/DaLAJ.json
seb/cache/KBLab__sentence-bert-swedish-cased/Da_Political_Comments.json
seb/cache/KBLab__sentence-bert-swedish-cased/DanFEVER.json
seb/cache/KBLab__sentence-bert-swedish-cased/LCC.json
seb/cache/KBLab__sentence-bert-swedish-cased/Language_Identification.json
seb/cache/KBLab__sentence-bert-swedish-cased/Massive_Intent.json
seb/cache/KBLab__sentence-bert-swedish-cased/Massive_Scenario.json
seb-0.13.11.dist-info/licenses/LICENSE
seb-0.13.11.dist-info/METADATA
seb-0.13.11.dist-info/WHEEL
seb-0.13.11.dist-info/entry_points.txt
seb-0.13.11.dist-info/top_level.txt
seb-0.13.11.dist-info/RECORD
