Metadata-Version: 2.4
Name: seb
Version: 0.13.11
Summary: Scandinavian Embedding Benchmark
Author-email: Kenneth Enevoldsen <Kennethcenevoldsen@gmail.com>
License: MIT License
Project-URL: homepage, https://github.com/KennethEnevoldsen/scandinavian-embedding-benchmark
Project-URL: repository, https://github.com/KennethEnevoldsen/scandinavian-embedding-benchmark
Project-URL: documentation, https://KennethEnevoldsen.github.io/scandinavian-embedding-benchmark/
Classifier: Operating System :: POSIX :: Linux
Classifier: Operating System :: MacOS :: MacOS X
Classifier: Programming Language :: Python :: 3.9
Classifier: Programming Language :: Python :: 3.10
Classifier: Programming Language :: Python :: 3.11
Classifier: Programming Language :: Python :: 3.12
Requires-Python: <3.13,>=3.9
License-File: LICENSE
Requires-Dist: mteb[beir]==1.1.1
Requires-Dist: pydantic>=2.1.0
Requires-Dist: catalogue>=2.0.8
Requires-Dist: radicli>=0.0.25
Requires-Dist: datasets<2.20.0
Requires-Dist: fsspec<=2023.9.2
Requires-Dist: psutil>=7.0.0
Provides-Extra: mistral
Requires-Dist: transformers>=4.31.0; extra == "mistral"
Provides-Extra: openai
Requires-Dist: openai>=0.27.4; extra == "openai"
Provides-Extra: voyageai
Requires-Dist: voyageai>=0.2.3; extra == "voyageai"
Provides-Extra: cohere
Requires-Dist: cohere>=4.34; extra == "cohere"
Provides-Extra: sonar
Requires-Dist: fairseq2>=0.1.0; extra == "sonar"
Requires-Dist: sonar-space>=0.2.1; extra == "sonar"
Provides-Extra: arctic
Requires-Dist: xformers>=0.0.10; extra == "arctic"
Provides-Extra: fasttext
Requires-Dist: pybind11>=2.11.0; extra == "fasttext"
Requires-Dist: fasttext-wheel>=0.9.0; extra == "fasttext"
Provides-Extra: jina
Requires-Dist: einops; extra == "jina"
Requires-Dist: numpy<2.0.0; extra == "jina"
Provides-Extra: llm2vec
Requires-Dist: ninja>=1.10.0; extra == "llm2vec"
Requires-Dist: llm2vec>=0.2.2; extra == "llm2vec"
Requires-Dist: flash-attn>=2.0.1; sys_platform == "linux" and extra == "llm2vec"
Dynamic: license-file
